pkg/__init__.py
pkg/rmctl.py
rmctl-0.1.1.dist-info/METADATA
rmctl-0.1.1.dist-info/RECORD
rmctl-0.1.1.dist-info/WHEEL
rmctl-0.1.1.dist-info/entry_points.txt
rmctl-0.1.1.dist-info/top_level.txt
