Metadata-Version: 2.1
Name: rmctl
Version: 0.1.1
Summary: Simple cli client for broadlink
Home-page: UNKNOWN
Author: mao2009
License: BSD
Platform: UNKNOWN
Requires-Dist: broadlink
